decayangle/__about__.py
decayangle/__init__.py
decayangle/backend.py
decayangle/config.py
decayangle/decay_topology.py
decayangle/kinematics.py
decayangle/lorentz.py
decayangle/numerics_helpers.py
decayangle-1.1.2.dist-info/METADATA
decayangle-1.1.2.dist-info/WHEEL
decayangle-1.1.2.dist-info/licenses/LICENSE.md
decayangle-1.1.2.dist-info/RECORD
