Metadata-Version: 2.3
Name: decayangle
Version: 1.1.2
Summary: A tool for wigner rotations in n-body decays
Project-URL: Documentation, https://kaihabermann.github.io/decayangle/
Project-URL: Issues, https://github.com/KaiHabermann/decayangle/issues
Project-URL: Source, https://github.com/KaiHabermann/decayangle
Author-email: Kai Habermann <kai.habermann@gmx.net>, Mikhail Mikhasenko <mikhail.mikhasenko@cern.ch>
License-Expression: MIT
License-File: LICENSE.md
Classifier: Development Status :: 4 - Beta
Classifier: Programming Language :: Python
Classifier: Programming Language :: Python :: 3.8
Classifier: Programming Language :: Python :: 3.9
Classifier: Programming Language :: Python :: 3.10
Classifier: Programming Language :: Python :: 3.11
Classifier: Programming Language :: Python :: 3.12
Classifier: Programming Language :: Python :: Implementation :: CPython
Classifier: Programming Language :: Python :: Implementation :: PyPy
Requires-Python: >=3.8
Requires-Dist: jax
Requires-Dist: jaxlib
Requires-Dist: networkx==3.0.0
Requires-Dist: numpy
Requires-Dist: tqdm
